[
    {
        "fileName": "Legal",
        "fileType": "directory",
        "fileContent": [
            {
                "fileName": "Terms of Service",
                "fileType": "file",
                "parentFolder": "Legal"
            },
            {
                "fileName": "Code of Conduct",
                "fileType": "file",
                "parentFolder": "Legal"
            },
            {
                "fileName": "Privacy Policy",
                "fileType": "file",
                "parentFolder": "Legal"
            }
        ]
    }
]
